pluralizefr/__init__.py
pluralizefr-0.1.1.dist-info/METADATA
pluralizefr-0.1.1.dist-info/WHEEL
pluralizefr-0.1.1.dist-info/licenses/LICENSE
pluralizefr-0.1.1.dist-info/RECORD
