Metadata-Version: 2.3
Name: pluralizefr
Version: 0.1.1
Summary: pluralize for french language
Project-URL: Homepage, https://github.com/sblondon/pluralizefr
Author-email: Yaal Coop <contact@yaal.coop>
License-Expression: BSD-3-Clause
License-File: LICENSE
Classifier: Intended Audience :: Developers
Classifier: License :: OSI Approved :: BSD License
Classifier: Operating System :: OS Independent
Classifier: Programming Language :: Python :: 3
Classifier: Topic :: Software Development
Requires-Python: >=3.8
